<Mixer id="1">
  <id>0</id>
  <targetPaint id="2">
    <id>129</id>
    <r>233.0</r>
    <g>106.0</g>
    <b>26.0</b>
  </targetPaint>
  <paints id="3">
    <Paint id="4">
      <id>130</id>
      <r>0.0</r>
      <g>0.0</g>
      <b>0.0</b>
    </Paint>
    <Paint id="5">
      <id>131</id>
      <r>1.0</r>
      <g>1.0</g>
      <b>1.0</b>
    </Paint>
    <Paint id="6">
      <id>132</id>
      <r>2.0</r>
      <g>2.0</g>
      <b>2.0</b>
    </Paint>
    <Paint id="7">
      <id>133</id>
      <r>3.0</r>
      <g>3.0</g>
      <b>3.0</b>
    </Paint>
    <Paint id="8">
      <id>134</id>
      <r>4.0</r>
      <g>4.0</g>
      <b>4.0</b>
    </Paint>
    <Paint id="9">
      <id>135</id>
      <r>5.0</r>
      <g>5.0</g>
      <b>5.0</b>
    </Paint>
    <Paint id="10">
      <id>136</id>
      <r>6.0</r>
      <g>6.0</g>
      <b>6.0</b>
    </Paint>
    <Paint id="11">
      <id>137</id>
      <r>7.0</r>
      <g>7.0</g>
      <b>7.0</b>
    </Paint>
    <Paint id="12">
      <id>138</id>
      <r>8.0</r>
      <g>8.0</g>
      <b>8.0</b>
    </Paint>
    <Paint id="13">
      <id>139</id>
      <r>9.0</r>
      <g>9.0</g>
      <b>9.0</b>
    </Paint>
    <Paint id="14">
      <id>140</id>
      <r>10.0</r>
      <g>10.0</g>
      <b>10.0</b>
    </Paint>
    <Paint id="15">
      <id>141</id>
      <r>11.0</r>
      <g>11.0</g>
      <b>11.0</b>
    </Paint>
    <Paint id="16">
      <id>142</id>
      <r>12.0</r>
      <g>12.0</g>
      <b>12.0</b>
    </Paint>
    <Paint id="17">
      <id>143</id>
      <r>13.0</r>
      <g>13.0</g>
      <b>13.0</b>
    </Paint>
    <Paint id="18">
      <id>144</id>
      <r>14.0</r>
      <g>14.0</g>
      <b>14.0</b>
    </Paint>
    <Paint id="19">
      <id>145</id>
      <r>15.0</r>
      <g>15.0</g>
      <b>15.0</b>
    </Paint>
    <Paint id="20">
      <id>146</id>
      <r>16.0</r>
      <g>16.0</g>
      <b>16.0</b>
    </Paint>
    <Paint id="21">
      <id>147</id>
      <r>17.0</r>
      <g>17.0</g>
      <b>17.0</b>
    </Paint>
    <Paint id="22">
      <id>148</id>
      <r>18.0</r>
      <g>18.0</g>
      <b>18.0</b>
    </Paint>
    <Paint id="23">
      <id>149</id>
      <r>19.0</r>
      <g>19.0</g>
      <b>19.0</b>
    </Paint>
    <Paint id="24">
      <id>150</id>
      <r>20.0</r>
      <g>20.0</g>
      <b>20.0</b>
    </Paint>
    <Paint id="25">
      <id>151</id>
      <r>21.0</r>
      <g>21.0</g>
      <b>21.0</b>
    </Paint>
    <Paint id="26">
      <id>152</id>
      <r>22.0</r>
      <g>22.0</g>
      <b>22.0</b>
    </Paint>
    <Paint id="27">
      <id>153</id>
      <r>23.0</r>
      <g>23.0</g>
      <b>23.0</b>
    </Paint>
    <Paint id="28">
      <id>154</id>
      <r>24.0</r>
      <g>24.0</g>
      <b>24.0</b>
    </Paint>
    <Paint id="29">
      <id>155</id>
      <r>25.0</r>
      <g>25.0</g>
      <b>25.0</b>
    </Paint>
    <Paint id="30">
      <id>156</id>
      <r>26.0</r>
      <g>26.0</g>
      <b>26.0</b>
    </Paint>
    <Paint id="31">
      <id>157</id>
      <r>27.0</r>
      <g>27.0</g>
      <b>27.0</b>
    </Paint>
    <Paint id="32">
      <id>158</id>
      <r>28.0</r>
      <g>28.0</g>
      <b>28.0</b>
    </Paint>
    <Paint id="33">
      <id>159</id>
      <r>29.0</r>
      <g>29.0</g>
      <b>29.0</b>
    </Paint>
    <Paint id="34">
      <id>160</id>
      <r>30.0</r>
      <g>30.0</g>
      <b>30.0</b>
    </Paint>
    <Paint id="35">
      <id>161</id>
      <r>31.0</r>
      <g>31.0</g>
      <b>31.0</b>
    </Paint>
    <Paint id="36">
      <id>162</id>
      <r>32.0</r>
      <g>32.0</g>
      <b>32.0</b>
    </Paint>
    <Paint id="37">
      <id>163</id>
      <r>33.0</r>
      <g>33.0</g>
      <b>33.0</b>
    </Paint>
    <Paint id="38">
      <id>164</id>
      <r>34.0</r>
      <g>34.0</g>
      <b>34.0</b>
    </Paint>
    <Paint id="39">
      <id>165</id>
      <r>35.0</r>
      <g>35.0</g>
      <b>35.0</b>
    </Paint>
    <Paint id="40">
      <id>166</id>
      <r>36.0</r>
      <g>36.0</g>
      <b>36.0</b>
    </Paint>
    <Paint id="41">
      <id>167</id>
      <r>37.0</r>
      <g>37.0</g>
      <b>37.0</b>
    </Paint>
    <Paint id="42">
      <id>168</id>
      <r>38.0</r>
      <g>38.0</g>
      <b>38.0</b>
    </Paint>
    <Paint id="43">
      <id>169</id>
      <r>39.0</r>
      <g>39.0</g>
      <b>39.0</b>
    </Paint>
    <Paint id="44">
      <id>170</id>
      <r>40.0</r>
      <g>40.0</g>
      <b>40.0</b>
    </Paint>
    <Paint id="45">
      <id>171</id>
      <r>41.0</r>
      <g>41.0</g>
      <b>41.0</b>
    </Paint>
    <Paint id="46">
      <id>172</id>
      <r>42.0</r>
      <g>42.0</g>
      <b>42.0</b>
    </Paint>
    <Paint id="47">
      <id>173</id>
      <r>43.0</r>
      <g>43.0</g>
      <b>43.0</b>
    </Paint>
    <Paint id="48">
      <id>174</id>
      <r>44.0</r>
      <g>44.0</g>
      <b>44.0</b>
    </Paint>
    <Paint id="49">
      <id>175</id>
      <r>45.0</r>
      <g>45.0</g>
      <b>45.0</b>
    </Paint>
    <Paint id="50">
      <id>176</id>
      <r>46.0</r>
      <g>46.0</g>
      <b>46.0</b>
    </Paint>
    <Paint id="51">
      <id>177</id>
      <r>47.0</r>
      <g>47.0</g>
      <b>47.0</b>
    </Paint>
    <Paint id="52">
      <id>178</id>
      <r>48.0</r>
      <g>48.0</g>
      <b>48.0</b>
    </Paint>
    <Paint id="53">
      <id>179</id>
      <r>49.0</r>
      <g>49.0</g>
      <b>49.0</b>
    </Paint>
    <Paint id="54">
      <id>180</id>
      <r>50.0</r>
      <g>50.0</g>
      <b>50.0</b>
    </Paint>
    <Paint id="55">
      <id>181</id>
      <r>51.0</r>
      <g>51.0</g>
      <b>51.0</b>
    </Paint>
    <Paint id="56">
      <id>182</id>
      <r>52.0</r>
      <g>52.0</g>
      <b>52.0</b>
    </Paint>
    <Paint id="57">
      <id>183</id>
      <r>53.0</r>
      <g>53.0</g>
      <b>53.0</b>
    </Paint>
    <Paint id="58">
      <id>184</id>
      <r>54.0</r>
      <g>54.0</g>
      <b>54.0</b>
    </Paint>
    <Paint id="59">
      <id>185</id>
      <r>55.0</r>
      <g>55.0</g>
      <b>55.0</b>
    </Paint>
    <Paint id="60">
      <id>186</id>
      <r>56.0</r>
      <g>56.0</g>
      <b>56.0</b>
    </Paint>
    <Paint id="61">
      <id>187</id>
      <r>57.0</r>
      <g>57.0</g>
      <b>57.0</b>
    </Paint>
    <Paint id="62">
      <id>188</id>
      <r>58.0</r>
      <g>58.0</g>
      <b>58.0</b>
    </Paint>
    <Paint id="63">
      <id>189</id>
      <r>59.0</r>
      <g>59.0</g>
      <b>59.0</b>
    </Paint>
    <Paint id="64">
      <id>190</id>
      <r>60.0</r>
      <g>60.0</g>
      <b>60.0</b>
    </Paint>
    <Paint id="65">
      <id>191</id>
      <r>61.0</r>
      <g>61.0</g>
      <b>61.0</b>
    </Paint>
    <Paint id="66">
      <id>192</id>
      <r>62.0</r>
      <g>62.0</g>
      <b>62.0</b>
    </Paint>
    <Paint id="67">
      <id>193</id>
      <r>63.0</r>
      <g>63.0</g>
      <b>63.0</b>
    </Paint>
    <Paint id="68">
      <id>194</id>
      <r>64.0</r>
      <g>64.0</g>
      <b>64.0</b>
    </Paint>
    <Paint id="69">
      <id>195</id>
      <r>65.0</r>
      <g>65.0</g>
      <b>65.0</b>
    </Paint>
    <Paint id="70">
      <id>196</id>
      <r>66.0</r>
      <g>66.0</g>
      <b>66.0</b>
    </Paint>
    <Paint id="71">
      <id>197</id>
      <r>67.0</r>
      <g>67.0</g>
      <b>67.0</b>
    </Paint>
    <Paint id="72">
      <id>198</id>
      <r>68.0</r>
      <g>68.0</g>
      <b>68.0</b>
    </Paint>
    <Paint id="73">
      <id>199</id>
      <r>69.0</r>
      <g>69.0</g>
      <b>69.0</b>
    </Paint>
    <Paint id="74">
      <id>200</id>
      <r>70.0</r>
      <g>70.0</g>
      <b>70.0</b>
    </Paint>
    <Paint id="75">
      <id>201</id>
      <r>71.0</r>
      <g>71.0</g>
      <b>71.0</b>
    </Paint>
    <Paint id="76">
      <id>202</id>
      <r>72.0</r>
      <g>72.0</g>
      <b>72.0</b>
    </Paint>
    <Paint id="77">
      <id>203</id>
      <r>73.0</r>
      <g>73.0</g>
      <b>73.0</b>
    </Paint>
    <Paint id="78">
      <id>204</id>
      <r>74.0</r>
      <g>74.0</g>
      <b>74.0</b>
    </Paint>
    <Paint id="79">
      <id>205</id>
      <r>75.0</r>
      <g>75.0</g>
      <b>75.0</b>
    </Paint>
    <Paint id="80">
      <id>206</id>
      <r>76.0</r>
      <g>76.0</g>
      <b>76.0</b>
    </Paint>
    <Paint id="81">
      <id>207</id>
      <r>77.0</r>
      <g>77.0</g>
      <b>77.0</b>
    </Paint>
    <Paint id="82">
      <id>208</id>
      <r>78.0</r>
      <g>78.0</g>
      <b>78.0</b>
    </Paint>
    <Paint id="83">
      <id>209</id>
      <r>79.0</r>
      <g>79.0</g>
      <b>79.0</b>
    </Paint>
    <Paint id="84">
      <id>210</id>
      <r>80.0</r>
      <g>80.0</g>
      <b>80.0</b>
    </Paint>
    <Paint id="85">
      <id>211</id>
      <r>81.0</r>
      <g>81.0</g>
      <b>81.0</b>
    </Paint>
    <Paint id="86">
      <id>212</id>
      <r>82.0</r>
      <g>82.0</g>
      <b>82.0</b>
    </Paint>
    <Paint id="87">
      <id>213</id>
      <r>83.0</r>
      <g>83.0</g>
      <b>83.0</b>
    </Paint>
    <Paint id="88">
      <id>214</id>
      <r>84.0</r>
      <g>84.0</g>
      <b>84.0</b>
    </Paint>
    <Paint id="89">
      <id>215</id>
      <r>85.0</r>
      <g>85.0</g>
      <b>85.0</b>
    </Paint>
    <Paint id="90">
      <id>216</id>
      <r>86.0</r>
      <g>86.0</g>
      <b>86.0</b>
    </Paint>
    <Paint id="91">
      <id>217</id>
      <r>87.0</r>
      <g>87.0</g>
      <b>87.0</b>
    </Paint>
    <Paint id="92">
      <id>218</id>
      <r>88.0</r>
      <g>88.0</g>
      <b>88.0</b>
    </Paint>
    <Paint id="93">
      <id>219</id>
      <r>89.0</r>
      <g>89.0</g>
      <b>89.0</b>
    </Paint>
    <Paint id="94">
      <id>220</id>
      <r>90.0</r>
      <g>90.0</g>
      <b>90.0</b>
    </Paint>
    <Paint id="95">
      <id>221</id>
      <r>91.0</r>
      <g>91.0</g>
      <b>91.0</b>
    </Paint>
    <Paint id="96">
      <id>222</id>
      <r>92.0</r>
      <g>92.0</g>
      <b>92.0</b>
    </Paint>
    <Paint id="97">
      <id>223</id>
      <r>93.0</r>
      <g>93.0</g>
      <b>93.0</b>
    </Paint>
    <Paint id="98">
      <id>224</id>
      <r>94.0</r>
      <g>94.0</g>
      <b>94.0</b>
    </Paint>
    <Paint id="99">
      <id>225</id>
      <r>95.0</r>
      <g>95.0</g>
      <b>95.0</b>
    </Paint>
    <Paint id="100">
      <id>226</id>
      <r>96.0</r>
      <g>96.0</g>
      <b>96.0</b>
    </Paint>
    <Paint id="101">
      <id>227</id>
      <r>97.0</r>
      <g>97.0</g>
      <b>97.0</b>
    </Paint>
    <Paint id="102">
      <id>228</id>
      <r>98.0</r>
      <g>98.0</g>
      <b>98.0</b>
    </Paint>
    <Paint id="103">
      <id>229</id>
      <r>99.0</r>
      <g>99.0</g>
      <b>99.0</b>
    </Paint>
    <Paint id="104">
      <id>230</id>
      <r>100.0</r>
      <g>100.0</g>
      <b>100.0</b>
    </Paint>
    <Paint id="105">
      <id>231</id>
      <r>101.0</r>
      <g>101.0</g>
      <b>101.0</b>
    </Paint>
    <Paint id="106">
      <id>232</id>
      <r>102.0</r>
      <g>102.0</g>
      <b>102.0</b>
    </Paint>
    <Paint id="107">
      <id>233</id>
      <r>103.0</r>
      <g>103.0</g>
      <b>103.0</b>
    </Paint>
    <Paint id="108">
      <id>234</id>
      <r>104.0</r>
      <g>104.0</g>
      <b>104.0</b>
    </Paint>
    <Paint id="109">
      <id>235</id>
      <r>105.0</r>
      <g>105.0</g>
      <b>105.0</b>
    </Paint>
    <Paint id="110">
      <id>236</id>
      <r>106.0</r>
      <g>106.0</g>
      <b>106.0</b>
    </Paint>
    <Paint id="111">
      <id>237</id>
      <r>107.0</r>
      <g>107.0</g>
      <b>107.0</b>
    </Paint>
    <Paint id="112">
      <id>238</id>
      <r>108.0</r>
      <g>108.0</g>
      <b>108.0</b>
    </Paint>
    <Paint id="113">
      <id>239</id>
      <r>109.0</r>
      <g>109.0</g>
      <b>109.0</b>
    </Paint>
    <Paint id="114">
      <id>240</id>
      <r>110.0</r>
      <g>110.0</g>
      <b>110.0</b>
    </Paint>
    <Paint id="115">
      <id>241</id>
      <r>111.0</r>
      <g>111.0</g>
      <b>111.0</b>
    </Paint>
    <Paint id="116">
      <id>242</id>
      <r>112.0</r>
      <g>112.0</g>
      <b>112.0</b>
    </Paint>
    <Paint id="117">
      <id>243</id>
      <r>113.0</r>
      <g>113.0</g>
      <b>113.0</b>
    </Paint>
    <Paint id="118">
      <id>244</id>
      <r>114.0</r>
      <g>114.0</g>
      <b>114.0</b>
    </Paint>
    <Paint id="119">
      <id>245</id>
      <r>115.0</r>
      <g>115.0</g>
      <b>115.0</b>
    </Paint>
    <Paint id="120">
      <id>246</id>
      <r>116.0</r>
      <g>116.0</g>
      <b>116.0</b>
    </Paint>
    <Paint id="121">
      <id>247</id>
      <r>117.0</r>
      <g>117.0</g>
      <b>117.0</b>
    </Paint>
    <Paint id="122">
      <id>248</id>
      <r>118.0</r>
      <g>118.0</g>
      <b>118.0</b>
    </Paint>
    <Paint id="123">
      <id>249</id>
      <r>119.0</r>
      <g>119.0</g>
      <b>119.0</b>
    </Paint>
    <Paint id="124">
      <id>250</id>
      <r>120.0</r>
      <g>120.0</g>
      <b>120.0</b>
    </Paint>
    <Paint id="125">
      <id>251</id>
      <r>121.0</r>
      <g>121.0</g>
      <b>121.0</b>
    </Paint>
    <Paint id="126">
      <id>252</id>
      <r>122.0</r>
      <g>122.0</g>
      <b>122.0</b>
    </Paint>
    <Paint id="127">
      <id>253</id>
      <r>123.0</r>
      <g>123.0</g>
      <b>123.0</b>
    </Paint>
    <Paint id="128">
      <id>254</id>
      <r>124.0</r>
      <g>124.0</g>
      <b>124.0</b>
    </Paint>
    <Paint id="129">
      <id>255</id>
      <r>125.0</r>
      <g>125.0</g>
      <b>125.0</b>
    </Paint>
    <Paint id="130">
      <id>256</id>
      <r>126.0</r>
      <g>126.0</g>
      <b>126.0</b>
    </Paint>
    <Paint id="131">
      <id>257</id>
      <r>127.0</r>
      <g>127.0</g>
      <b>127.0</b>
    </Paint>
    <Paint id="132">
      <id>258</id>
      <r>128.0</r>
      <g>128.0</g>
      <b>128.0</b>
    </Paint>
    <Paint id="133">
      <id>259</id>
      <r>129.0</r>
      <g>129.0</g>
      <b>129.0</b>
    </Paint>
    <Paint id="134">
      <id>260</id>
      <r>130.0</r>
      <g>130.0</g>
      <b>130.0</b>
    </Paint>
    <Paint id="135">
      <id>261</id>
      <r>131.0</r>
      <g>131.0</g>
      <b>131.0</b>
    </Paint>
    <Paint id="136">
      <id>262</id>
      <r>132.0</r>
      <g>132.0</g>
      <b>132.0</b>
    </Paint>
    <Paint id="137">
      <id>263</id>
      <r>133.0</r>
      <g>133.0</g>
      <b>133.0</b>
    </Paint>
    <Paint id="138">
      <id>264</id>
      <r>134.0</r>
      <g>134.0</g>
      <b>134.0</b>
    </Paint>
    <Paint id="139">
      <id>265</id>
      <r>135.0</r>
      <g>135.0</g>
      <b>135.0</b>
    </Paint>
    <Paint id="140">
      <id>266</id>
      <r>136.0</r>
      <g>136.0</g>
      <b>136.0</b>
    </Paint>
    <Paint id="141">
      <id>267</id>
      <r>137.0</r>
      <g>137.0</g>
      <b>137.0</b>
    </Paint>
    <Paint id="142">
      <id>268</id>
      <r>138.0</r>
      <g>138.0</g>
      <b>138.0</b>
    </Paint>
    <Paint id="143">
      <id>269</id>
      <r>139.0</r>
      <g>139.0</g>
      <b>139.0</b>
    </Paint>
    <Paint id="144">
      <id>270</id>
      <r>140.0</r>
      <g>140.0</g>
      <b>140.0</b>
    </Paint>
    <Paint id="145">
      <id>271</id>
      <r>141.0</r>
      <g>141.0</g>
      <b>141.0</b>
    </Paint>
    <Paint id="146">
      <id>272</id>
      <r>142.0</r>
      <g>142.0</g>
      <b>142.0</b>
    </Paint>
    <Paint id="147">
      <id>273</id>
      <r>143.0</r>
      <g>143.0</g>
      <b>143.0</b>
    </Paint>
    <Paint id="148">
      <id>274</id>
      <r>144.0</r>
      <g>144.0</g>
      <b>144.0</b>
    </Paint>
    <Paint id="149">
      <id>275</id>
      <r>145.0</r>
      <g>145.0</g>
      <b>145.0</b>
    </Paint>
    <Paint id="150">
      <id>276</id>
      <r>146.0</r>
      <g>146.0</g>
      <b>146.0</b>
    </Paint>
    <Paint id="151">
      <id>277</id>
      <r>147.0</r>
      <g>147.0</g>
      <b>147.0</b>
    </Paint>
    <Paint id="152">
      <id>278</id>
      <r>148.0</r>
      <g>148.0</g>
      <b>148.0</b>
    </Paint>
    <Paint id="153">
      <id>279</id>
      <r>149.0</r>
      <g>149.0</g>
      <b>149.0</b>
    </Paint>
    <Paint id="154">
      <id>280</id>
      <r>150.0</r>
      <g>150.0</g>
      <b>150.0</b>
    </Paint>
    <Paint id="155">
      <id>281</id>
      <r>151.0</r>
      <g>151.0</g>
      <b>151.0</b>
    </Paint>
    <Paint id="156">
      <id>282</id>
      <r>152.0</r>
      <g>152.0</g>
      <b>152.0</b>
    </Paint>
    <Paint id="157">
      <id>283</id>
      <r>153.0</r>
      <g>153.0</g>
      <b>153.0</b>
    </Paint>
    <Paint id="158">
      <id>284</id>
      <r>154.0</r>
      <g>154.0</g>
      <b>154.0</b>
    </Paint>
    <Paint id="159">
      <id>285</id>
      <r>155.0</r>
      <g>155.0</g>
      <b>155.0</b>
    </Paint>
    <Paint id="160">
      <id>286</id>
      <r>156.0</r>
      <g>156.0</g>
      <b>156.0</b>
    </Paint>
    <Paint id="161">
      <id>287</id>
      <r>157.0</r>
      <g>157.0</g>
      <b>157.0</b>
    </Paint>
    <Paint id="162">
      <id>288</id>
      <r>158.0</r>
      <g>158.0</g>
      <b>158.0</b>
    </Paint>
    <Paint id="163">
      <id>289</id>
      <r>159.0</r>
      <g>159.0</g>
      <b>159.0</b>
    </Paint>
    <Paint id="164">
      <id>290</id>
      <r>160.0</r>
      <g>160.0</g>
      <b>160.0</b>
    </Paint>
    <Paint id="165">
      <id>291</id>
      <r>161.0</r>
      <g>161.0</g>
      <b>161.0</b>
    </Paint>
    <Paint id="166">
      <id>292</id>
      <r>162.0</r>
      <g>162.0</g>
      <b>162.0</b>
    </Paint>
    <Paint id="167">
      <id>293</id>
      <r>163.0</r>
      <g>163.0</g>
      <b>163.0</b>
    </Paint>
    <Paint id="168">
      <id>294</id>
      <r>164.0</r>
      <g>164.0</g>
      <b>164.0</b>
    </Paint>
    <Paint id="169">
      <id>295</id>
      <r>165.0</r>
      <g>165.0</g>
      <b>165.0</b>
    </Paint>
    <Paint id="170">
      <id>296</id>
      <r>166.0</r>
      <g>166.0</g>
      <b>166.0</b>
    </Paint>
    <Paint id="171">
      <id>297</id>
      <r>167.0</r>
      <g>167.0</g>
      <b>167.0</b>
    </Paint>
    <Paint id="172">
      <id>298</id>
      <r>168.0</r>
      <g>168.0</g>
      <b>168.0</b>
    </Paint>
    <Paint id="173">
      <id>299</id>
      <r>169.0</r>
      <g>169.0</g>
      <b>169.0</b>
    </Paint>
    <Paint id="174">
      <id>300</id>
      <r>170.0</r>
      <g>170.0</g>
      <b>170.0</b>
    </Paint>
    <Paint id="175">
      <id>301</id>
      <r>171.0</r>
      <g>171.0</g>
      <b>171.0</b>
    </Paint>
    <Paint id="176">
      <id>302</id>
      <r>172.0</r>
      <g>172.0</g>
      <b>172.0</b>
    </Paint>
    <Paint id="177">
      <id>303</id>
      <r>173.0</r>
      <g>173.0</g>
      <b>173.0</b>
    </Paint>
    <Paint id="178">
      <id>304</id>
      <r>174.0</r>
      <g>174.0</g>
      <b>174.0</b>
    </Paint>
    <Paint id="179">
      <id>305</id>
      <r>175.0</r>
      <g>175.0</g>
      <b>175.0</b>
    </Paint>
    <Paint id="180">
      <id>306</id>
      <r>176.0</r>
      <g>176.0</g>
      <b>176.0</b>
    </Paint>
    <Paint id="181">
      <id>307</id>
      <r>177.0</r>
      <g>177.0</g>
      <b>177.0</b>
    </Paint>
    <Paint id="182">
      <id>308</id>
      <r>178.0</r>
      <g>178.0</g>
      <b>178.0</b>
    </Paint>
    <Paint id="183">
      <id>309</id>
      <r>179.0</r>
      <g>179.0</g>
      <b>179.0</b>
    </Paint>
    <Paint id="184">
      <id>310</id>
      <r>180.0</r>
      <g>180.0</g>
      <b>180.0</b>
    </Paint>
    <Paint id="185">
      <id>311</id>
      <r>181.0</r>
      <g>181.0</g>
      <b>181.0</b>
    </Paint>
    <Paint id="186">
      <id>312</id>
      <r>182.0</r>
      <g>182.0</g>
      <b>182.0</b>
    </Paint>
    <Paint id="187">
      <id>313</id>
      <r>183.0</r>
      <g>183.0</g>
      <b>183.0</b>
    </Paint>
    <Paint id="188">
      <id>314</id>
      <r>184.0</r>
      <g>184.0</g>
      <b>184.0</b>
    </Paint>
    <Paint id="189">
      <id>315</id>
      <r>185.0</r>
      <g>185.0</g>
      <b>185.0</b>
    </Paint>
    <Paint id="190">
      <id>316</id>
      <r>186.0</r>
      <g>186.0</g>
      <b>186.0</b>
    </Paint>
    <Paint id="191">
      <id>317</id>
      <r>187.0</r>
      <g>187.0</g>
      <b>187.0</b>
    </Paint>
    <Paint id="192">
      <id>318</id>
      <r>188.0</r>
      <g>188.0</g>
      <b>188.0</b>
    </Paint>
    <Paint id="193">
      <id>319</id>
      <r>189.0</r>
      <g>189.0</g>
      <b>189.0</b>
    </Paint>
    <Paint id="194">
      <id>320</id>
      <r>190.0</r>
      <g>190.0</g>
      <b>190.0</b>
    </Paint>
    <Paint id="195">
      <id>321</id>
      <r>191.0</r>
      <g>191.0</g>
      <b>191.0</b>
    </Paint>
    <Paint id="196">
      <id>322</id>
      <r>192.0</r>
      <g>192.0</g>
      <b>192.0</b>
    </Paint>
    <Paint id="197">
      <id>323</id>
      <r>193.0</r>
      <g>193.0</g>
      <b>193.0</b>
    </Paint>
    <Paint id="198">
      <id>324</id>
      <r>194.0</r>
      <g>194.0</g>
      <b>194.0</b>
    </Paint>
    <Paint id="199">
      <id>325</id>
      <r>195.0</r>
      <g>195.0</g>
      <b>195.0</b>
    </Paint>
    <Paint id="200">
      <id>326</id>
      <r>196.0</r>
      <g>196.0</g>
      <b>196.0</b>
    </Paint>
    <Paint id="201">
      <id>327</id>
      <r>197.0</r>
      <g>197.0</g>
      <b>197.0</b>
    </Paint>
    <Paint id="202">
      <id>328</id>
      <r>198.0</r>
      <g>198.0</g>
      <b>198.0</b>
    </Paint>
    <Paint id="203">
      <id>329</id>
      <r>199.0</r>
      <g>199.0</g>
      <b>199.0</b>
    </Paint>
    <Paint id="204">
      <id>330</id>
      <r>200.0</r>
      <g>200.0</g>
      <b>200.0</b>
    </Paint>
    <Paint id="205">
      <id>331</id>
      <r>201.0</r>
      <g>201.0</g>
      <b>201.0</b>
    </Paint>
    <Paint id="206">
      <id>332</id>
      <r>202.0</r>
      <g>202.0</g>
      <b>202.0</b>
    </Paint>
    <Paint id="207">
      <id>333</id>
      <r>203.0</r>
      <g>203.0</g>
      <b>203.0</b>
    </Paint>
    <Paint id="208">
      <id>334</id>
      <r>204.0</r>
      <g>204.0</g>
      <b>204.0</b>
    </Paint>
    <Paint id="209">
      <id>335</id>
      <r>205.0</r>
      <g>205.0</g>
      <b>205.0</b>
    </Paint>
    <Paint id="210">
      <id>336</id>
      <r>206.0</r>
      <g>206.0</g>
      <b>206.0</b>
    </Paint>
    <Paint id="211">
      <id>337</id>
      <r>207.0</r>
      <g>207.0</g>
      <b>207.0</b>
    </Paint>
    <Paint id="212">
      <id>338</id>
      <r>208.0</r>
      <g>208.0</g>
      <b>208.0</b>
    </Paint>
    <Paint id="213">
      <id>339</id>
      <r>209.0</r>
      <g>209.0</g>
      <b>209.0</b>
    </Paint>
    <Paint id="214">
      <id>340</id>
      <r>210.0</r>
      <g>210.0</g>
      <b>210.0</b>
    </Paint>
    <Paint id="215">
      <id>341</id>
      <r>211.0</r>
      <g>211.0</g>
      <b>211.0</b>
    </Paint>
    <Paint id="216">
      <id>342</id>
      <r>212.0</r>
      <g>212.0</g>
      <b>212.0</b>
    </Paint>
    <Paint id="217">
      <id>343</id>
      <r>213.0</r>
      <g>213.0</g>
      <b>213.0</b>
    </Paint>
    <Paint id="218">
      <id>344</id>
      <r>214.0</r>
      <g>214.0</g>
      <b>214.0</b>
    </Paint>
    <Paint id="219">
      <id>345</id>
      <r>215.0</r>
      <g>215.0</g>
      <b>215.0</b>
    </Paint>
    <Paint id="220">
      <id>346</id>
      <r>216.0</r>
      <g>216.0</g>
      <b>216.0</b>
    </Paint>
    <Paint id="221">
      <id>347</id>
      <r>217.0</r>
      <g>217.0</g>
      <b>217.0</b>
    </Paint>
    <Paint id="222">
      <id>348</id>
      <r>218.0</r>
      <g>218.0</g>
      <b>218.0</b>
    </Paint>
    <Paint id="223">
      <id>349</id>
      <r>219.0</r>
      <g>219.0</g>
      <b>219.0</b>
    </Paint>
    <Paint id="224">
      <id>350</id>
      <r>220.0</r>
      <g>220.0</g>
      <b>220.0</b>
    </Paint>
    <Paint id="225">
      <id>351</id>
      <r>221.0</r>
      <g>221.0</g>
      <b>221.0</b>
    </Paint>
    <Paint id="226">
      <id>352</id>
      <r>222.0</r>
      <g>222.0</g>
      <b>222.0</b>
    </Paint>
    <Paint id="227">
      <id>353</id>
      <r>223.0</r>
      <g>223.0</g>
      <b>223.0</b>
    </Paint>
    <Paint id="228">
      <id>354</id>
      <r>224.0</r>
      <g>224.0</g>
      <b>224.0</b>
    </Paint>
    <Paint id="229">
      <id>355</id>
      <r>225.0</r>
      <g>225.0</g>
      <b>225.0</b>
    </Paint>
    <Paint id="230">
      <id>356</id>
      <r>226.0</r>
      <g>226.0</g>
      <b>226.0</b>
    </Paint>
    <Paint id="231">
      <id>357</id>
      <r>227.0</r>
      <g>227.0</g>
      <b>227.0</b>
    </Paint>
    <Paint id="232">
      <id>358</id>
      <r>228.0</r>
      <g>228.0</g>
      <b>228.0</b>
    </Paint>
    <Paint id="233">
      <id>359</id>
      <r>229.0</r>
      <g>229.0</g>
      <b>229.0</b>
    </Paint>
    <Paint id="234">
      <id>360</id>
      <r>230.0</r>
      <g>230.0</g>
      <b>230.0</b>
    </Paint>
    <Paint id="235">
      <id>361</id>
      <r>231.0</r>
      <g>231.0</g>
      <b>231.0</b>
    </Paint>
    <Paint id="236">
      <id>362</id>
      <r>232.0</r>
      <g>232.0</g>
      <b>232.0</b>
    </Paint>
    <Paint id="237">
      <id>363</id>
      <r>233.0</r>
      <g>233.0</g>
      <b>233.0</b>
    </Paint>
    <Paint id="238">
      <id>364</id>
      <r>234.0</r>
      <g>234.0</g>
      <b>234.0</b>
    </Paint>
    <Paint id="239">
      <id>365</id>
      <r>235.0</r>
      <g>235.0</g>
      <b>235.0</b>
    </Paint>
    <Paint id="240">
      <id>366</id>
      <r>236.0</r>
      <g>236.0</g>
      <b>236.0</b>
    </Paint>
    <Paint id="241">
      <id>367</id>
      <r>237.0</r>
      <g>237.0</g>
      <b>237.0</b>
    </Paint>
    <Paint id="242">
      <id>368</id>
      <r>238.0</r>
      <g>238.0</g>
      <b>238.0</b>
    </Paint>
    <Paint id="243">
      <id>369</id>
      <r>239.0</r>
      <g>239.0</g>
      <b>239.0</b>
    </Paint>
    <Paint id="244">
      <id>370</id>
      <r>240.0</r>
      <g>240.0</g>
      <b>240.0</b>
    </Paint>
    <Paint id="245">
      <id>371</id>
      <r>241.0</r>
      <g>241.0</g>
      <b>241.0</b>
    </Paint>
    <Paint id="246">
      <id>372</id>
      <r>242.0</r>
      <g>242.0</g>
      <b>242.0</b>
    </Paint>
    <Paint id="247">
      <id>373</id>
      <r>243.0</r>
      <g>243.0</g>
      <b>243.0</b>
    </Paint>
    <Paint id="248">
      <id>374</id>
      <r>244.0</r>
      <g>244.0</g>
      <b>244.0</b>
    </Paint>
    <Paint id="249">
      <id>375</id>
      <r>245.0</r>
      <g>245.0</g>
      <b>245.0</b>
    </Paint>
    <Paint id="250">
      <id>376</id>
      <r>246.0</r>
      <g>246.0</g>
      <b>246.0</b>
    </Paint>
    <Paint id="251">
      <id>377</id>
      <r>247.0</r>
      <g>247.0</g>
      <b>247.0</b>
    </Paint>
    <Paint id="252">
      <id>378</id>
      <r>248.0</r>
      <g>248.0</g>
      <b>248.0</b>
    </Paint>
    <Paint id="253">
      <id>379</id>
      <r>249.0</r>
      <g>249.0</g>
      <b>249.0</b>
    </Paint>
    <Paint id="254">
      <id>380</id>
      <r>250.0</r>
      <g>250.0</g>
      <b>250.0</b>
    </Paint>
    <Paint id="255">
      <id>381</id>
      <r>251.0</r>
      <g>251.0</g>
      <b>251.0</b>
    </Paint>
    <Paint id="256">
      <id>382</id>
      <r>252.0</r>
      <g>252.0</g>
      <b>252.0</b>
    </Paint>
    <Paint id="257">
      <id>383</id>
      <r>253.0</r>
      <g>253.0</g>
      <b>253.0</b>
    </Paint>
    <Paint id="258">
      <id>384</id>
      <r>254.0</r>
      <g>254.0</g>
      <b>254.0</b>
    </Paint>
    <Paint id="259">
      <id>385</id>
      <r>255.0</r>
      <g>255.0</g>
      <b>255.0</b>
    </Paint>
  </paints>
  <paintMixes id="260">
    <PaintMix id="261">
      <id>0</id>
      <paint reference="4"/>
      <amount>0</amount>
    </PaintMix>
    <PaintMix id="262">
      <id>1</id>
      <paint reference="5"/>
      <amount>0</amount>
    </PaintMix>
    <PaintMix id="263">
      <id>2</id>
      <paint reference="6"/>
      <amount>0</amount>
    </PaintMix>
    <PaintMix id="264">
      <id>3</id>
      <paint reference="7"/>
      <amount>0</amount>
    </PaintMix>
    <PaintMix id="265">
      <id>4</id>
      <paint reference="8"/>
      <amount>0</amount>
    </PaintMix>
    <PaintMix id="266">
      <id>5</id>
      <paint reference="9"/>
      <amount>0</amount>
    </PaintMix>
    <PaintMix id="267">
      <id>6</id>
      <paint reference="10"/>
      <amount>0</amount>
    </PaintMix>
    <PaintMix id="268">
      <id>7</id>
      <paint reference="11"/>
      <amount>0</amount>
    </PaintMix>
    <PaintMix id="269">
      <id>8</id>
      <paint reference="12"/>
      <amount>0</amount>
    </PaintMix>
    <PaintMix id="270">
      <id>9</id>
      <paint reference="13"/>
      <amount>0</amount>
    </PaintMix>
    <PaintMix id="271">
      <id>10</id>
      <paint reference="14"/>
      <amount>0</amount>
    </PaintMix>
    <PaintMix id="272">
      <id>11</id>
      <paint reference="15"/>
      <amount>0</amount>
    </PaintMix>
    <PaintMix id="273">
      <id>12</id>
      <paint reference="16"/>
      <amount>0</amount>
    </PaintMix>
    <PaintMix id="274">
      <id>13</id>
      <paint reference="17"/>
      <amount>0</amount>
    </PaintMix>
    <PaintMix id="275">
      <id>14</id>
      <paint reference="18"/>
      <amount>0</amount>
    </PaintMix>
    <PaintMix id="276">
      <id>15</id>
      <paint reference="19"/>
      <amount>0</amount>
    </PaintMix>
    <PaintMix id="277">
      <id>16</id>
      <paint reference="20"/>
      <amount>0</amount>
    </PaintMix>
    <PaintMix id="278">
      <id>17</id>
      <paint reference="21"/>
      <amount>0</amount>
    </PaintMix>
    <PaintMix id="279">
      <id>18</id>
      <paint reference="22"/>
      <amount>0</amount>
    </PaintMix>
    <PaintMix id="280">
      <id>19</id>
      <paint reference="23"/>
      <amount>0</amount>
    </PaintMix>
    <PaintMix id="281">
      <id>20</id>
      <paint reference="24"/>
      <amount>0</amount>
    </PaintMix>
    <PaintMix id="282">
      <id>21</id>
      <paint reference="25"/>
      <amount>0</amount>
    </PaintMix>
    <PaintMix id="283">
      <id>22</id>
      <paint reference="26"/>
      <amount>0</amount>
    </PaintMix>
    <PaintMix id="284">
      <id>23</id>
      <paint reference="27"/>
      <amount>0</amount>
    </PaintMix>
    <PaintMix id="285">
      <id>24</id>
      <paint reference="28"/>
      <amount>0</amount>
    </PaintMix>
    <PaintMix id="286">
      <id>25</id>
      <paint reference="29"/>
      <amount>0</amount>
    </PaintMix>
    <PaintMix id="287">
      <id>26</id>
      <paint reference="30"/>
      <amount>0</amount>
    </PaintMix>
    <PaintMix id="288">
      <id>27</id>
      <paint reference="31"/>
      <amount>0</amount>
    </PaintMix>
    <PaintMix id="289">
      <id>28</id>
      <paint reference="32"/>
      <amount>0</amount>
    </PaintMix>
    <PaintMix id="290">
      <id>29</id>
      <paint reference="33"/>
      <amount>0</amount>
    </PaintMix>
    <PaintMix id="291">
      <id>30</id>
      <paint reference="34"/>
      <amount>0</amount>
    </PaintMix>
    <PaintMix id="292">
      <id>31</id>
      <paint reference="35"/>
      <amount>0</amount>
    </PaintMix>
    <PaintMix id="293">
      <id>32</id>
      <paint reference="36"/>
      <amount>0</amount>
    </PaintMix>
    <PaintMix id="294">
      <id>33</id>
      <paint reference="37"/>
      <amount>0</amount>
    </PaintMix>
    <PaintMix id="295">
      <id>34</id>
      <paint reference="38"/>
      <amount>0</amount>
    </PaintMix>
    <PaintMix id="296">
      <id>35</id>
      <paint reference="39"/>
      <amount>0</amount>
    </PaintMix>
    <PaintMix id="297">
      <id>36</id>
      <paint reference="40"/>
      <amount>0</amount>
    </PaintMix>
    <PaintMix id="298">
      <id>37</id>
      <paint reference="41"/>
      <amount>0</amount>
    </PaintMix>
    <PaintMix id="299">
      <id>38</id>
      <paint reference="42"/>
      <amount>0</amount>
    </PaintMix>
    <PaintMix id="300">
      <id>39</id>
      <paint reference="43"/>
      <amount>0</amount>
    </PaintMix>
    <PaintMix id="301">
      <id>40</id>
      <paint reference="44"/>
      <amount>0</amount>
    </PaintMix>
    <PaintMix id="302">
      <id>41</id>
      <paint reference="45"/>
      <amount>0</amount>
    </PaintMix>
    <PaintMix id="303">
      <id>42</id>
      <paint reference="46"/>
      <amount>0</amount>
    </PaintMix>
    <PaintMix id="304">
      <id>43</id>
      <paint reference="47"/>
      <amount>0</amount>
    </PaintMix>
    <PaintMix id="305">
      <id>44</id>
      <paint reference="48"/>
      <amount>0</amount>
    </PaintMix>
    <PaintMix id="306">
      <id>45</id>
      <paint reference="49"/>
      <amount>0</amount>
    </PaintMix>
    <PaintMix id="307">
      <id>46</id>
      <paint reference="50"/>
      <amount>0</amount>
    </PaintMix>
    <PaintMix id="308">
      <id>47</id>
      <paint reference="51"/>
      <amount>0</amount>
    </PaintMix>
    <PaintMix id="309">
      <id>48</id>
      <paint reference="52"/>
      <amount>0</amount>
    </PaintMix>
    <PaintMix id="310">
      <id>49</id>
      <paint reference="53"/>
      <amount>0</amount>
    </PaintMix>
    <PaintMix id="311">
      <id>50</id>
      <paint reference="54"/>
      <amount>0</amount>
    </PaintMix>
    <PaintMix id="312">
      <id>51</id>
      <paint reference="55"/>
      <amount>0</amount>
    </PaintMix>
    <PaintMix id="313">
      <id>52</id>
      <paint reference="56"/>
      <amount>0</amount>
    </PaintMix>
    <PaintMix id="314">
      <id>53</id>
      <paint reference="57"/>
      <amount>0</amount>
    </PaintMix>
    <PaintMix id="315">
      <id>54</id>
      <paint reference="58"/>
      <amount>0</amount>
    </PaintMix>
    <PaintMix id="316">
      <id>55</id>
      <paint reference="59"/>
      <amount>0</amount>
    </PaintMix>
    <PaintMix id="317">
      <id>56</id>
      <paint reference="60"/>
      <amount>0</amount>
    </PaintMix>
    <PaintMix id="318">
      <id>57</id>
      <paint reference="61"/>
      <amount>0</amount>
    </PaintMix>
    <PaintMix id="319">
      <id>58</id>
      <paint reference="62"/>
      <amount>0</amount>
    </PaintMix>
    <PaintMix id="320">
      <id>59</id>
      <paint reference="63"/>
      <amount>0</amount>
    </PaintMix>
    <PaintMix id="321">
      <id>60</id>
      <paint reference="64"/>
      <amount>0</amount>
    </PaintMix>
    <PaintMix id="322">
      <id>61</id>
      <paint reference="65"/>
      <amount>0</amount>
    </PaintMix>
    <PaintMix id="323">
      <id>62</id>
      <paint reference="66"/>
      <amount>0</amount>
    </PaintMix>
    <PaintMix id="324">
      <id>63</id>
      <paint reference="67"/>
      <amount>0</amount>
    </PaintMix>
    <PaintMix id="325">
      <id>64</id>
      <paint reference="68"/>
      <amount>0</amount>
    </PaintMix>
    <PaintMix id="326">
      <id>65</id>
      <paint reference="69"/>
      <amount>0</amount>
    </PaintMix>
    <PaintMix id="327">
      <id>66</id>
      <paint reference="70"/>
      <amount>0</amount>
    </PaintMix>
    <PaintMix id="328">
      <id>67</id>
      <paint reference="71"/>
      <amount>0</amount>
    </PaintMix>
    <PaintMix id="329">
      <id>68</id>
      <paint reference="72"/>
      <amount>0</amount>
    </PaintMix>
    <PaintMix id="330">
      <id>69</id>
      <paint reference="73"/>
      <amount>0</amount>
    </PaintMix>
    <PaintMix id="331">
      <id>70</id>
      <paint reference="74"/>
      <amount>0</amount>
    </PaintMix>
    <PaintMix id="332">
      <id>71</id>
      <paint reference="75"/>
      <amount>0</amount>
    </PaintMix>
    <PaintMix id="333">
      <id>72</id>
      <paint reference="76"/>
      <amount>0</amount>
    </PaintMix>
    <PaintMix id="334">
      <id>73</id>
      <paint reference="77"/>
      <amount>0</amount>
    </PaintMix>
    <PaintMix id="335">
      <id>74</id>
      <paint reference="78"/>
      <amount>0</amount>
    </PaintMix>
    <PaintMix id="336">
      <id>75</id>
      <paint reference="79"/>
      <amount>0</amount>
    </PaintMix>
    <PaintMix id="337">
      <id>76</id>
      <paint reference="80"/>
      <amount>0</amount>
    </PaintMix>
    <PaintMix id="338">
      <id>77</id>
      <paint reference="81"/>
      <amount>0</amount>
    </PaintMix>
    <PaintMix id="339">
      <id>78</id>
      <paint reference="82"/>
      <amount>0</amount>
    </PaintMix>
    <PaintMix id="340">
      <id>79</id>
      <paint reference="83"/>
      <amount>0</amount>
    </PaintMix>
    <PaintMix id="341">
      <id>80</id>
      <paint reference="84"/>
      <amount>0</amount>
    </PaintMix>
    <PaintMix id="342">
      <id>81</id>
      <paint reference="85"/>
      <amount>0</amount>
    </PaintMix>
    <PaintMix id="343">
      <id>82</id>
      <paint reference="86"/>
      <amount>0</amount>
    </PaintMix>
    <PaintMix id="344">
      <id>83</id>
      <paint reference="87"/>
      <amount>0</amount>
    </PaintMix>
    <PaintMix id="345">
      <id>84</id>
      <paint reference="88"/>
      <amount>0</amount>
    </PaintMix>
    <PaintMix id="346">
      <id>85</id>
      <paint reference="89"/>
      <amount>0</amount>
    </PaintMix>
    <PaintMix id="347">
      <id>86</id>
      <paint reference="90"/>
      <amount>0</amount>
    </PaintMix>
    <PaintMix id="348">
      <id>87</id>
      <paint reference="91"/>
      <amount>0</amount>
    </PaintMix>
    <PaintMix id="349">
      <id>88</id>
      <paint reference="92"/>
      <amount>0</amount>
    </PaintMix>
    <PaintMix id="350">
      <id>89</id>
      <paint reference="93"/>
      <amount>0</amount>
    </PaintMix>
    <PaintMix id="351">
      <id>90</id>
      <paint reference="94"/>
      <amount>0</amount>
    </PaintMix>
    <PaintMix id="352">
      <id>91</id>
      <paint reference="95"/>
      <amount>0</amount>
    </PaintMix>
    <PaintMix id="353">
      <id>92</id>
      <paint reference="96"/>
      <amount>0</amount>
    </PaintMix>
    <PaintMix id="354">
      <id>93</id>
      <paint reference="97"/>
      <amount>0</amount>
    </PaintMix>
    <PaintMix id="355">
      <id>94</id>
      <paint reference="98"/>
      <amount>0</amount>
    </PaintMix>
    <PaintMix id="356">
      <id>95</id>
      <paint reference="99"/>
      <amount>0</amount>
    </PaintMix>
    <PaintMix id="357">
      <id>96</id>
      <paint reference="100"/>
      <amount>0</amount>
    </PaintMix>
    <PaintMix id="358">
      <id>97</id>
      <paint reference="101"/>
      <amount>0</amount>
    </PaintMix>
    <PaintMix id="359">
      <id>98</id>
      <paint reference="102"/>
      <amount>0</amount>
    </PaintMix>
    <PaintMix id="360">
      <id>99</id>
      <paint reference="103"/>
      <amount>0</amount>
    </PaintMix>
    <PaintMix id="361">
      <id>100</id>
      <paint reference="104"/>
      <amount>0</amount>
    </PaintMix>
    <PaintMix id="362">
      <id>101</id>
      <paint reference="105"/>
      <amount>0</amount>
    </PaintMix>
    <PaintMix id="363">
      <id>102</id>
      <paint reference="106"/>
      <amount>0</amount>
    </PaintMix>
    <PaintMix id="364">
      <id>103</id>
      <paint reference="107"/>
      <amount>0</amount>
    </PaintMix>
    <PaintMix id="365">
      <id>104</id>
      <paint reference="108"/>
      <amount>0</amount>
    </PaintMix>
    <PaintMix id="366">
      <id>105</id>
      <paint reference="109"/>
      <amount>0</amount>
    </PaintMix>
    <PaintMix id="367">
      <id>106</id>
      <paint reference="110"/>
      <amount>0</amount>
    </PaintMix>
    <PaintMix id="368">
      <id>107</id>
      <paint reference="111"/>
      <amount>0</amount>
    </PaintMix>
    <PaintMix id="369">
      <id>108</id>
      <paint reference="112"/>
      <amount>0</amount>
    </PaintMix>
    <PaintMix id="370">
      <id>109</id>
      <paint reference="113"/>
      <amount>0</amount>
    </PaintMix>
    <PaintMix id="371">
      <id>110</id>
      <paint reference="114"/>
      <amount>0</amount>
    </PaintMix>
    <PaintMix id="372">
      <id>111</id>
      <paint reference="115"/>
      <amount>0</amount>
    </PaintMix>
    <PaintMix id="373">
      <id>112</id>
      <paint reference="116"/>
      <amount>0</amount>
    </PaintMix>
    <PaintMix id="374">
      <id>113</id>
      <paint reference="117"/>
      <amount>0</amount>
    </PaintMix>
    <PaintMix id="375">
      <id>114</id>
      <paint reference="118"/>
      <amount>0</amount>
    </PaintMix>
    <PaintMix id="376">
      <id>115</id>
      <paint reference="119"/>
      <amount>0</amount>
    </PaintMix>
    <PaintMix id="377">
      <id>116</id>
      <paint reference="120"/>
      <amount>0</amount>
    </PaintMix>
    <PaintMix id="378">
      <id>117</id>
      <paint reference="121"/>
      <amount>0</amount>
    </PaintMix>
    <PaintMix id="379">
      <id>118</id>
      <paint reference="122"/>
      <amount>0</amount>
    </PaintMix>
    <PaintMix id="380">
      <id>119</id>
      <paint reference="123"/>
      <amount>0</amount>
    </PaintMix>
    <PaintMix id="381">
      <id>120</id>
      <paint reference="124"/>
      <amount>0</amount>
    </PaintMix>
    <PaintMix id="382">
      <id>121</id>
      <paint reference="125"/>
      <amount>0</amount>
    </PaintMix>
    <PaintMix id="383">
      <id>122</id>
      <paint reference="126"/>
      <amount>0</amount>
    </PaintMix>
    <PaintMix id="384">
      <id>123</id>
      <paint reference="127"/>
      <amount>0</amount>
    </PaintMix>
    <PaintMix id="385">
      <id>124</id>
      <paint reference="128"/>
      <amount>0</amount>
    </PaintMix>
    <PaintMix id="386">
      <id>125</id>
      <paint reference="129"/>
      <amount>0</amount>
    </PaintMix>
    <PaintMix id="387">
      <id>126</id>
      <paint reference="130"/>
      <amount>0</amount>
    </PaintMix>
    <PaintMix id="388">
      <id>127</id>
      <paint reference="131"/>
      <amount>0</amount>
    </PaintMix>
    <PaintMix id="389">
      <id>128</id>
      <paint reference="132"/>
      <amount>0</amount>
    </PaintMix>
    <PaintMix id="390">
      <id>129</id>
      <paint reference="133"/>
      <amount>0</amount>
    </PaintMix>
    <PaintMix id="391">
      <id>130</id>
      <paint reference="134"/>
      <amount>0</amount>
    </PaintMix>
    <PaintMix id="392">
      <id>131</id>
      <paint reference="135"/>
      <amount>0</amount>
    </PaintMix>
    <PaintMix id="393">
      <id>132</id>
      <paint reference="136"/>
      <amount>0</amount>
    </PaintMix>
    <PaintMix id="394">
      <id>133</id>
      <paint reference="137"/>
      <amount>0</amount>
    </PaintMix>
    <PaintMix id="395">
      <id>134</id>
      <paint reference="138"/>
      <amount>0</amount>
    </PaintMix>
    <PaintMix id="396">
      <id>135</id>
      <paint reference="139"/>
      <amount>0</amount>
    </PaintMix>
    <PaintMix id="397">
      <id>136</id>
      <paint reference="140"/>
      <amount>0</amount>
    </PaintMix>
    <PaintMix id="398">
      <id>137</id>
      <paint reference="141"/>
      <amount>0</amount>
    </PaintMix>
    <PaintMix id="399">
      <id>138</id>
      <paint reference="142"/>
      <amount>0</amount>
    </PaintMix>
    <PaintMix id="400">
      <id>139</id>
      <paint reference="143"/>
      <amount>0</amount>
    </PaintMix>
    <PaintMix id="401">
      <id>140</id>
      <paint reference="144"/>
      <amount>0</amount>
    </PaintMix>
    <PaintMix id="402">
      <id>141</id>
      <paint reference="145"/>
      <amount>0</amount>
    </PaintMix>
    <PaintMix id="403">
      <id>142</id>
      <paint reference="146"/>
      <amount>0</amount>
    </PaintMix>
    <PaintMix id="404">
      <id>143</id>
      <paint reference="147"/>
      <amount>0</amount>
    </PaintMix>
    <PaintMix id="405">
      <id>144</id>
      <paint reference="148"/>
      <amount>0</amount>
    </PaintMix>
    <PaintMix id="406">
      <id>145</id>
      <paint reference="149"/>
      <amount>0</amount>
    </PaintMix>
    <PaintMix id="407">
      <id>146</id>
      <paint reference="150"/>
      <amount>0</amount>
    </PaintMix>
    <PaintMix id="408">
      <id>147</id>
      <paint reference="151"/>
      <amount>0</amount>
    </PaintMix>
    <PaintMix id="409">
      <id>148</id>
      <paint reference="152"/>
      <amount>0</amount>
    </PaintMix>
    <PaintMix id="410">
      <id>149</id>
      <paint reference="153"/>
      <amount>0</amount>
    </PaintMix>
    <PaintMix id="411">
      <id>150</id>
      <paint reference="154"/>
      <amount>0</amount>
    </PaintMix>
    <PaintMix id="412">
      <id>151</id>
      <paint reference="155"/>
      <amount>0</amount>
    </PaintMix>
    <PaintMix id="413">
      <id>152</id>
      <paint reference="156"/>
      <amount>0</amount>
    </PaintMix>
    <PaintMix id="414">
      <id>153</id>
      <paint reference="157"/>
      <amount>0</amount>
    </PaintMix>
    <PaintMix id="415">
      <id>154</id>
      <paint reference="158"/>
      <amount>0</amount>
    </PaintMix>
    <PaintMix id="416">
      <id>155</id>
      <paint reference="159"/>
      <amount>0</amount>
    </PaintMix>
    <PaintMix id="417">
      <id>156</id>
      <paint reference="160"/>
      <amount>0</amount>
    </PaintMix>
    <PaintMix id="418">
      <id>157</id>
      <paint reference="161"/>
      <amount>0</amount>
    </PaintMix>
    <PaintMix id="419">
      <id>158</id>
      <paint reference="162"/>
      <amount>0</amount>
    </PaintMix>
    <PaintMix id="420">
      <id>159</id>
      <paint reference="163"/>
      <amount>0</amount>
    </PaintMix>
    <PaintMix id="421">
      <id>160</id>
      <paint reference="164"/>
      <amount>0</amount>
    </PaintMix>
    <PaintMix id="422">
      <id>161</id>
      <paint reference="165"/>
      <amount>0</amount>
    </PaintMix>
    <PaintMix id="423">
      <id>162</id>
      <paint reference="166"/>
      <amount>0</amount>
    </PaintMix>
    <PaintMix id="424">
      <id>163</id>
      <paint reference="167"/>
      <amount>0</amount>
    </PaintMix>
    <PaintMix id="425">
      <id>164</id>
      <paint reference="168"/>
      <amount>0</amount>
    </PaintMix>
    <PaintMix id="426">
      <id>165</id>
      <paint reference="169"/>
      <amount>0</amount>
    </PaintMix>
    <PaintMix id="427">
      <id>166</id>
      <paint reference="170"/>
      <amount>0</amount>
    </PaintMix>
    <PaintMix id="428">
      <id>167</id>
      <paint reference="171"/>
      <amount>0</amount>
    </PaintMix>
    <PaintMix id="429">
      <id>168</id>
      <paint reference="172"/>
      <amount>0</amount>
    </PaintMix>
    <PaintMix id="430">
      <id>169</id>
      <paint reference="173"/>
      <amount>0</amount>
    </PaintMix>
    <PaintMix id="431">
      <id>170</id>
      <paint reference="174"/>
      <amount>0</amount>
    </PaintMix>
    <PaintMix id="432">
      <id>171</id>
      <paint reference="175"/>
      <amount>0</amount>
    </PaintMix>
    <PaintMix id="433">
      <id>172</id>
      <paint reference="176"/>
      <amount>0</amount>
    </PaintMix>
    <PaintMix id="434">
      <id>173</id>
      <paint reference="177"/>
      <amount>0</amount>
    </PaintMix>
    <PaintMix id="435">
      <id>174</id>
      <paint reference="178"/>
      <amount>0</amount>
    </PaintMix>
    <PaintMix id="436">
      <id>175</id>
      <paint reference="179"/>
      <amount>0</amount>
    </PaintMix>
    <PaintMix id="437">
      <id>176</id>
      <paint reference="180"/>
      <amount>0</amount>
    </PaintMix>
    <PaintMix id="438">
      <id>177</id>
      <paint reference="181"/>
      <amount>0</amount>
    </PaintMix>
    <PaintMix id="439">
      <id>178</id>
      <paint reference="182"/>
      <amount>0</amount>
    </PaintMix>
    <PaintMix id="440">
      <id>179</id>
      <paint reference="183"/>
      <amount>0</amount>
    </PaintMix>
    <PaintMix id="441">
      <id>180</id>
      <paint reference="184"/>
      <amount>0</amount>
    </PaintMix>
    <PaintMix id="442">
      <id>181</id>
      <paint reference="185"/>
      <amount>0</amount>
    </PaintMix>
    <PaintMix id="443">
      <id>182</id>
      <paint reference="186"/>
      <amount>0</amount>
    </PaintMix>
    <PaintMix id="444">
      <id>183</id>
      <paint reference="187"/>
      <amount>0</amount>
    </PaintMix>
    <PaintMix id="445">
      <id>184</id>
      <paint reference="188"/>
      <amount>0</amount>
    </PaintMix>
    <PaintMix id="446">
      <id>185</id>
      <paint reference="189"/>
      <amount>0</amount>
    </PaintMix>
    <PaintMix id="447">
      <id>186</id>
      <paint reference="190"/>
      <amount>0</amount>
    </PaintMix>
    <PaintMix id="448">
      <id>187</id>
      <paint reference="191"/>
      <amount>0</amount>
    </PaintMix>
    <PaintMix id="449">
      <id>188</id>
      <paint reference="192"/>
      <amount>0</amount>
    </PaintMix>
    <PaintMix id="450">
      <id>189</id>
      <paint reference="193"/>
      <amount>0</amount>
    </PaintMix>
    <PaintMix id="451">
      <id>190</id>
      <paint reference="194"/>
      <amount>0</amount>
    </PaintMix>
    <PaintMix id="452">
      <id>191</id>
      <paint reference="195"/>
      <amount>0</amount>
    </PaintMix>
    <PaintMix id="453">
      <id>192</id>
      <paint reference="196"/>
      <amount>0</amount>
    </PaintMix>
    <PaintMix id="454">
      <id>193</id>
      <paint reference="197"/>
      <amount>0</amount>
    </PaintMix>
    <PaintMix id="455">
      <id>194</id>
      <paint reference="198"/>
      <amount>0</amount>
    </PaintMix>
    <PaintMix id="456">
      <id>195</id>
      <paint reference="199"/>
      <amount>0</amount>
    </PaintMix>
    <PaintMix id="457">
      <id>196</id>
      <paint reference="200"/>
      <amount>0</amount>
    </PaintMix>
    <PaintMix id="458">
      <id>197</id>
      <paint reference="201"/>
      <amount>0</amount>
    </PaintMix>
    <PaintMix id="459">
      <id>198</id>
      <paint reference="202"/>
      <amount>0</amount>
    </PaintMix>
    <PaintMix id="460">
      <id>199</id>
      <paint reference="203"/>
      <amount>0</amount>
    </PaintMix>
    <PaintMix id="461">
      <id>200</id>
      <paint reference="204"/>
      <amount>0</amount>
    </PaintMix>
    <PaintMix id="462">
      <id>201</id>
      <paint reference="205"/>
      <amount>0</amount>
    </PaintMix>
    <PaintMix id="463">
      <id>202</id>
      <paint reference="206"/>
      <amount>0</amount>
    </PaintMix>
    <PaintMix id="464">
      <id>203</id>
      <paint reference="207"/>
      <amount>0</amount>
    </PaintMix>
    <PaintMix id="465">
      <id>204</id>
      <paint reference="208"/>
      <amount>0</amount>
    </PaintMix>
    <PaintMix id="466">
      <id>205</id>
      <paint reference="209"/>
      <amount>0</amount>
    </PaintMix>
    <PaintMix id="467">
      <id>206</id>
      <paint reference="210"/>
      <amount>0</amount>
    </PaintMix>
    <PaintMix id="468">
      <id>207</id>
      <paint reference="211"/>
      <amount>0</amount>
    </PaintMix>
    <PaintMix id="469">
      <id>208</id>
      <paint reference="212"/>
      <amount>0</amount>
    </PaintMix>
    <PaintMix id="470">
      <id>209</id>
      <paint reference="213"/>
      <amount>0</amount>
    </PaintMix>
    <PaintMix id="471">
      <id>210</id>
      <paint reference="214"/>
      <amount>0</amount>
    </PaintMix>
    <PaintMix id="472">
      <id>211</id>
      <paint reference="215"/>
      <amount>0</amount>
    </PaintMix>
    <PaintMix id="473">
      <id>212</id>
      <paint reference="216"/>
      <amount>0</amount>
    </PaintMix>
    <PaintMix id="474">
      <id>213</id>
      <paint reference="217"/>
      <amount>0</amount>
    </PaintMix>
    <PaintMix id="475">
      <id>214</id>
      <paint reference="218"/>
      <amount>0</amount>
    </PaintMix>
    <PaintMix id="476">
      <id>215</id>
      <paint reference="219"/>
      <amount>0</amount>
    </PaintMix>
    <PaintMix id="477">
      <id>216</id>
      <paint reference="220"/>
      <amount>0</amount>
    </PaintMix>
    <PaintMix id="478">
      <id>217</id>
      <paint reference="221"/>
      <amount>0</amount>
    </PaintMix>
    <PaintMix id="479">
      <id>218</id>
      <paint reference="222"/>
      <amount>0</amount>
    </PaintMix>
    <PaintMix id="480">
      <id>219</id>
      <paint reference="223"/>
      <amount>0</amount>
    </PaintMix>
    <PaintMix id="481">
      <id>220</id>
      <paint reference="224"/>
      <amount>0</amount>
    </PaintMix>
    <PaintMix id="482">
      <id>221</id>
      <paint reference="225"/>
      <amount>0</amount>
    </PaintMix>
    <PaintMix id="483">
      <id>222</id>
      <paint reference="226"/>
      <amount>0</amount>
    </PaintMix>
    <PaintMix id="484">
      <id>223</id>
      <paint reference="227"/>
      <amount>0</amount>
    </PaintMix>
    <PaintMix id="485">
      <id>224</id>
      <paint reference="228"/>
      <amount>0</amount>
    </PaintMix>
    <PaintMix id="486">
      <id>225</id>
      <paint reference="229"/>
      <amount>0</amount>
    </PaintMix>
    <PaintMix id="487">
      <id>226</id>
      <paint reference="230"/>
      <amount>0</amount>
    </PaintMix>
    <PaintMix id="488">
      <id>227</id>
      <paint reference="231"/>
      <amount>0</amount>
    </PaintMix>
    <PaintMix id="489">
      <id>228</id>
      <paint reference="232"/>
      <amount>0</amount>
    </PaintMix>
    <PaintMix id="490">
      <id>229</id>
      <paint reference="233"/>
      <amount>0</amount>
    </PaintMix>
    <PaintMix id="491">
      <id>230</id>
      <paint reference="234"/>
      <amount>0</amount>
    </PaintMix>
    <PaintMix id="492">
      <id>231</id>
      <paint reference="235"/>
      <amount>0</amount>
    </PaintMix>
    <PaintMix id="493">
      <id>232</id>
      <paint reference="236"/>
      <amount>0</amount>
    </PaintMix>
    <PaintMix id="494">
      <id>233</id>
      <paint reference="237"/>
      <amount>0</amount>
    </PaintMix>
    <PaintMix id="495">
      <id>234</id>
      <paint reference="238"/>
      <amount>0</amount>
    </PaintMix>
    <PaintMix id="496">
      <id>235</id>
      <paint reference="239"/>
      <amount>0</amount>
    </PaintMix>
    <PaintMix id="497">
      <id>236</id>
      <paint reference="240"/>
      <amount>0</amount>
    </PaintMix>
    <PaintMix id="498">
      <id>237</id>
      <paint reference="241"/>
      <amount>0</amount>
    </PaintMix>
    <PaintMix id="499">
      <id>238</id>
      <paint reference="242"/>
      <amount>0</amount>
    </PaintMix>
    <PaintMix id="500">
      <id>239</id>
      <paint reference="243"/>
      <amount>0</amount>
    </PaintMix>
    <PaintMix id="501">
      <id>240</id>
      <paint reference="244"/>
      <amount>0</amount>
    </PaintMix>
    <PaintMix id="502">
      <id>241</id>
      <paint reference="245"/>
      <amount>0</amount>
    </PaintMix>
    <PaintMix id="503">
      <id>242</id>
      <paint reference="246"/>
      <amount>0</amount>
    </PaintMix>
    <PaintMix id="504">
      <id>243</id>
      <paint reference="247"/>
      <amount>0</amount>
    </PaintMix>
    <PaintMix id="505">
      <id>244</id>
      <paint reference="248"/>
      <amount>0</amount>
    </PaintMix>
    <PaintMix id="506">
      <id>245</id>
      <paint reference="249"/>
      <amount>0</amount>
    </PaintMix>
    <PaintMix id="507">
      <id>246</id>
      <paint reference="250"/>
      <amount>0</amount>
    </PaintMix>
    <PaintMix id="508">
      <id>247</id>
      <paint reference="251"/>
      <amount>0</amount>
    </PaintMix>
    <PaintMix id="509">
      <id>248</id>
      <paint reference="252"/>
      <amount>0</amount>
    </PaintMix>
    <PaintMix id="510">
      <id>249</id>
      <paint reference="253"/>
      <amount>0</amount>
    </PaintMix>
    <PaintMix id="511">
      <id>250</id>
      <paint reference="254"/>
      <amount>0</amount>
    </PaintMix>
    <PaintMix id="512">
      <id>251</id>
      <paint reference="255"/>
      <amount>0</amount>
    </PaintMix>
    <PaintMix id="513">
      <id>252</id>
      <paint reference="256"/>
      <amount>0</amount>
    </PaintMix>
    <PaintMix id="514">
      <id>253</id>
      <paint reference="257"/>
      <amount>0</amount>
    </PaintMix>
    <PaintMix id="515">
      <id>254</id>
      <paint reference="258"/>
      <amount>0</amount>
    </PaintMix>
    <PaintMix id="516">
      <id>255</id>
      <paint reference="259"/>
      <amount>0</amount>
    </PaintMix>
  </paintMixes>
  <score id="517">0hard/0medium/0soft</score>
</Mixer>